essencia/__init__.py
essencia/__main__.py
essencia/py.typed
essencia/analytics/__init__.py
essencia/analytics/aggregators.py
essencia/analytics/analyzers.py
essencia/analytics/reports.py
essencia/api/__init__.py
essencia/api/app.py
essencia/api/dependencies.py
essencia/api/routers/__init__.py
essencia/api/routers/admin.py
essencia/api/routers/appointments.py
essencia/api/routers/auth.py
essencia/api/routers/laboratory.py
essencia/api/routers/medications.py
essencia/api/routers/mental_health.py
essencia/api/routers/patients.py
essencia/api/routers/vital_signs.py
essencia/cache/__init__.py
essencia/cache/async_cache.py
essencia/cache/cache_integration.py
essencia/cache/intelligent_cache.py
essencia/cache/patterns.py
essencia/cache/strategies.py
essencia/cli/__init__.py
essencia/cli/doctor.py
essencia/cli/main.py
essencia/cli/templates.py
essencia/cli/commands/__init__.py
essencia/cli/commands/create.py
essencia/cli/commands/db.py
essencia/cli/commands/generate.py
essencia/cli/commands/medical.py
essencia/cli/commands/security.py
essencia/cli/commands/test.py
essencia/core/__init__.py
essencia/core/config.py
essencia/core/exceptions.py
essencia/database/__init__.py
essencia/database/abstract.py
essencia/database/async_mongodb.py
essencia/database/mongodb.py
essencia/database/mongodb_adapter.py
essencia/database/postgresql_adapter.py
essencia/database/redis_client.py
essencia/database/sync_mongodb.py
essencia/fields/__init__.py
essencia/fields/base_fields.py
essencia/fields/encrypted_fields.py
essencia/fields/example.py
essencia/fields/medical_encrypted_fields.py
essencia/graphql/__init__.py
essencia/graphql/app.py
essencia/graphql/context.py
essencia/graphql/resolvers.py
essencia/graphql/schema.py
essencia/graphql/types.py
essencia/integrations/__init__.py
essencia/integrations/anvisa.py
essencia/integrations/sus.py
essencia/integrations/flet/README.md
essencia/integrations/flet/__init__.py
essencia/integrations/flet/components.py
essencia-1.11.0.dist-info/METADATA
essencia-1.11.0.dist-info/WHEEL
essencia-1.11.0.dist-info/entry_points.txt
essencia-1.11.0.dist-info/licenses/LICENSE
essencia-1.11.0.dist-info/RECORD
