Metadata-Version: 2.4
Name: essencia
Version: 1.11.0
Summary: A comprehensive Python framework for building secure medical and business applications with advanced security features and Flet integration
Project-URL: Homepage, https://github.com/arantesdv/essencia
Project-URL: Bug Tracker, https://github.com/arantesdv/essencia/issues
Project-URL: Documentation, https://github.com/arantesdv/essencia#readme
Author-email: Daniel Arantes <arantesdv@me.com>
License: MIT
License-File: LICENSE
Keywords: brazil,encryption,flet,framework,medical,mongodb
Classifier: Development Status :: 3 - Alpha
Classifier: Intended Audience :: Developers
Classifier: License :: OSI Approved :: MIT License
Classifier: Programming Language :: Python :: 3
Classifier: Programming Language :: Python :: 3.12
Classifier: Topic :: Software Development :: Libraries :: Application Frameworks
Classifier: Topic :: Software Development :: Libraries :: Python Modules
Requires-Python: >=3.12
Requires-Dist: aiofiles>=23.2.1
Requires-Dist: aioredis>=2.0.1
Requires-Dist: bson>=0.5.10
Requires-Dist: cryptography>=44.0.0
Requires-Dist: fastapi>=0.100.0
Requires-Dist: flet[all]>=0.28.3
Requires-Dist: httpx>=0.27.0
Requires-Dist: itsdangerous>=2.0.0
Requires-Dist: motor>=3.7.1
Requires-Dist: numpy>=1.26.0
Requires-Dist: psutil>=5.9.0
Requires-Dist: pydantic[email]>=2.11.5
Requires-Dist: pyjwt>=2.8.0
Requires-Dist: pymongo>=4.13.0
Requires-Dist: python-dateutil>=2.8.0
Requires-Dist: python-dotenv>=1.0.0
Requires-Dist: redis>=6.1.0
Requires-Dist: rich>=13.0.0
Requires-Dist: starlette>=0.27.0
Requires-Dist: typer[all]>=0.12.0
Requires-Dist: unidecode>=1.3.8
Requires-Dist: uvicorn[standard]>=0.23.0
Provides-Extra: all
Requires-Dist: argon2-cffi>=23.0.0; extra == 'all'
Requires-Dist: asyncpg>=0.29.0; extra == 'all'
Requires-Dist: bcrypt>=4.0.0; extra == 'all'
Requires-Dist: factory-boy>=3.3.0; extra == 'all'
Requires-Dist: faker>=30.0.0; extra == 'all'
Requires-Dist: flet[all]>=0.28.3; extra == 'all'
Requires-Dist: httpx>=0.27.0; extra == 'all'
Requires-Dist: motor>=3.7.1; extra == 'all'
Requires-Dist: psycopg2-binary>=2.9.0; extra == 'all'
Requires-Dist: pytest-asyncio>=0.23.0; extra == 'all'
Requires-Dist: pytest-cov>=5.0.0; extra == 'all'
Requires-Dist: pytest-mock>=3.14.0; extra == 'all'
Requires-Dist: pytest-timeout>=2.3.0; extra == 'all'
Requires-Dist: pytest-xdist>=3.6.0; extra == 'all'
Requires-Dist: pytest>=8.0.0; extra == 'all'
Requires-Dist: respx>=0.21.0; extra == 'all'
Requires-Dist: sqlalchemy[asyncio]>=2.0.0; extra == 'all'
Provides-Extra: async
Requires-Dist: motor>=3.7.1; extra == 'async'
Provides-Extra: dev
Requires-Dist: black>=24.0.0; extra == 'dev'
Requires-Dist: flake8>=7.0.0; extra == 'dev'
Requires-Dist: isort>=5.13.0; extra == 'dev'
Requires-Dist: mypy>=1.11.0; extra == 'dev'
Requires-Dist: pre-commit>=4.0.0; extra == 'dev'
Requires-Dist: ruff>=0.8.0; extra == 'dev'
Provides-Extra: flet
Requires-Dist: flet[all]>=0.28.3; extra == 'flet'
Provides-Extra: graphql
Requires-Dist: graphene>=3.3.0; extra == 'graphql'
Requires-Dist: strawberry-graphql[fastapi]>=0.235.0; extra == 'graphql'
Provides-Extra: mobile
Requires-Dist: aiofiles>=23.2.1; extra == 'mobile'
Requires-Dist: flet[all]>=0.28.3; extra == 'mobile'
Provides-Extra: monitoring
Requires-Dist: opentelemetry-api>=1.24.0; extra == 'monitoring'
Requires-Dist: opentelemetry-exporter-jaeger>=1.21.0; extra == 'monitoring'
Requires-Dist: opentelemetry-exporter-otlp>=1.24.0; extra == 'monitoring'
Requires-Dist: opentelemetry-exporter-zipkin>=1.24.0; extra == 'monitoring'
Requires-Dist: opentelemetry-instrumentation-fastapi>=0.45b0; extra == 'monitoring'
Requires-Dist: opentelemetry-instrumentation-pymongo>=0.45b0; extra == 'monitoring'
Requires-Dist: opentelemetry-instrumentation-redis>=0.45b0; extra == 'monitoring'
Requires-Dist: opentelemetry-instrumentation-requests>=0.45b0; extra == 'monitoring'
Requires-Dist: opentelemetry-instrumentation>=0.45b0; extra == 'monitoring'
Requires-Dist: opentelemetry-sdk>=1.24.0; extra == 'monitoring'
Requires-Dist: prometheus-client>=0.20.0; extra == 'monitoring'
Provides-Extra: postgresql
Requires-Dist: asyncpg>=0.29.0; extra == 'postgresql'
Requires-Dist: psycopg2-binary>=2.9.0; extra == 'postgresql'
Requires-Dist: sqlalchemy[asyncio]>=2.0.0; extra == 'postgresql'
Provides-Extra: security
Requires-Dist: argon2-cffi>=23.0.0; extra == 'security'
Requires-Dist: bcrypt>=4.0.0; extra == 'security'
Provides-Extra: test
Requires-Dist: factory-boy>=3.3.0; extra == 'test'
Requires-Dist: faker>=30.0.0; extra == 'test'
Requires-Dist: httpx>=0.27.0; extra == 'test'
Requires-Dist: pytest-asyncio>=0.23.0; extra == 'test'
Requires-Dist: pytest-cov>=5.0.0; extra == 'test'
Requires-Dist: pytest-mock>=3.14.0; extra == 'test'
Requires-Dist: pytest-timeout>=2.3.0; extra == 'test'
Requires-Dist: pytest-xdist>=3.6.0; extra == 'test'
Requires-Dist: pytest>=8.0.0; extra == 'test'
Requires-Dist: respx>=0.21.0; extra == 'test'
Provides-Extra: websocket
Requires-Dist: python-socketio>=5.11.0; extra == 'websocket'
Requires-Dist: websockets>=12.0; extra == 'websocket'
